template_engines/VERSION.md
template_engines/__init__.py
template_engines/apps.py
template_engines/backends/__init__.py
template_engines/backends/abstract.py
template_engines/backends/docx.py
template_engines/backends/odt.py
template_engines/backends/utils.py
template_engines/backends/utils_docx.py
template_engines/backends/utils_odt.py
template_engines/templatetags/__init__.py
template_engines/templatetags/docx_tags.py
template_engines/templatetags/odt_tags.py
template_engines/templatetags/utils.py
template_engines/tests/__init__.py
template_engines/tests/settings.py
template_engines/tests/test_docx_template.py
template_engines/tests/test_odt_template.py
django_template_engines-1.2.28.dist-info/LICENSE
django_template_engines-1.2.28.dist-info/METADATA
django_template_engines-1.2.28.dist-info/WHEEL
django_template_engines-1.2.28.dist-info/top_level.txt
django_template_engines-1.2.28.dist-info/RECORD
